<annotation>
            <folder>JPEGImages</folder>
            <filename>133.jpg</filename>
            <size>
                <width>424</width>
                <height>271</height>
                <depth>3</depth>
            </size>
            <segmented>0</segmented>
    <object>
                <name>bank_card_number</name>
                <pose>Unspecified</pose>
                <truncated>0</truncated>
                <difficult>0</difficult>
                <bndbox>
                    <xmin>44</xmin>
                    <ymin>150</ymin>
                    <xmax>381</xmax>
                    <ymax>177</ymax>
                </bndbox>
            </object>
</annotation>