<annotation>
            <folder>JPEGImages</folder>
            <filename>1462.jpg</filename>
            <size>
                <width>322</width>
                <height>202</height>
                <depth>3</depth>
            </size>
            <segmented>0</segmented>
    <object>
                <name>bank_card_number</name>
                <pose>Unspecified</pose>
                <truncated>0</truncated>
                <difficult>0</difficult>
                <bndbox>
                    <xmin>31</xmin>
                    <ymin>110</ymin>
                    <xmax>291</xmax>
                    <ymax>132</ymax>
                </bndbox>
            </object>
</annotation>