<annotation>
            <folder>JPEGImages</folder>
            <filename>2133.jpg</filename>
            <size>
                <width>675</width>
                <height>439</height>
                <depth>3</depth>
            </size>
            <segmented>0</segmented>
    <object>
                <name>bank_card_number</name>
                <pose>Unspecified</pose>
                <truncated>0</truncated>
                <difficult>0</difficult>
                <bndbox>
                    <xmin>67</xmin>
                    <ymin>234</ymin>
                    <xmax>612</xmax>
                    <ymax>284</ymax>
                </bndbox>
            </object>
</annotation>